odoo/addons/sale_product_company/README.rst
odoo/addons/sale_product_company/__init__.py
odoo/addons/sale_product_company/__manifest__.py
odoo/addons/sale_product_company/i18n/fr.po
odoo/addons/sale_product_company/i18n/it.po
odoo/addons/sale_product_company/i18n/sale_product_company.pot
odoo/addons/sale_product_company/migrations/16.0.2.0.0/pre-migration.py
odoo/addons/sale_product_company/models/__init__.py
odoo/addons/sale_product_company/models/product_template.py
odoo/addons/sale_product_company/readme/CONTRIBUTORS.rst
odoo/addons/sale_product_company/readme/DESCRIPTION.rst
odoo/addons/sale_product_company/static/description/icon.png
odoo/addons/sale_product_company/static/description/index.html
odoo/addons/sale_product_company/tests/__init__.py
odoo/addons/sale_product_company/tests/test_sale_partner_company.py
odoo/addons/sale_product_company/views/product_template_view.xml
odoo/addons/sale_product_company/views/sale_order_view.xml
odoo_addon_sale_product_company-16.0.2.0.0.5.dist-info/METADATA
odoo_addon_sale_product_company-16.0.2.0.0.5.dist-info/WHEEL
odoo_addon_sale_product_company-16.0.2.0.0.5.dist-info/top_level.txt
odoo_addon_sale_product_company-16.0.2.0.0.5.dist-info/RECORD
