Metadata-Version: 2.1
Name: odoo-addon-sale-product-company
Version: 16.0.2.0.0.5
Summary: Set selling companies on product
Home-page: https://github.com/OCA/multi-company
Author: Camptocamp, Odoo Community Association (OCA)
Author-email: support@odoo-community.org
License: AGPL-3
Platform: UNKNOWN
Classifier: Programming Language :: Python
Classifier: Framework :: Odoo
Classifier: Framework :: Odoo :: 16.0
Classifier: License :: OSI Approved :: GNU Affero General Public License v3
Classifier: Development Status :: 3 - Alpha
Requires-Python: >=3.10
Requires-Dist: odoo-addon-base-view-inheritance-extension <16.1dev,>=16.0dev
Requires-Dist: odoo <16.1dev,>=16.0a
